tinystream.py
tinystream-0.1.18.dist-info/licenses/LICENSE
tinystream-0.1.18.dist-info/METADATA
tinystream-0.1.18.dist-info/WHEEL
tinystream-0.1.18.dist-info/top_level.txt
tinystream-0.1.18.dist-info/RECORD
