Metadata-Version: 2.4
Name: tinystream
Version: 0.1.18
Summary: Yet another python streams library
Home-page: https://github.com/mreiche/python-streams
Author: Mike Reiche
License-File: LICENSE
Dynamic: author
Dynamic: description
Dynamic: description-content-type
Dynamic: home-page
Dynamic: license-file
Dynamic: summary
